llama_index/vector_stores/chroma/__init__.py
llama_index/vector_stores/chroma/base.py
flying_delta_vector_stores_chroma-0.1.0.dist-info/METADATA
flying_delta_vector_stores_chroma-0.1.0.dist-info/WHEEL
flying_delta_vector_stores_chroma-0.1.0.dist-info/RECORD
